rubato/__init__.cpython-310-darwin.so
rubato/__init__.py
rubato/game.cpython-310-darwin.so
rubato/game.py
rubato/misc.cpython-310-darwin.so
rubato/misc.py
rubato/__pyinstaller/__init__.py
rubato/__pyinstaller/hook-rubato.py
rubato/c_src/__init__.py
rubato/c_src/c_draw.cpython-310-darwin.so
rubato/c_src/c_draw.py
rubato/c_src/cdraw.pxd
rubato/static/__init__.py
rubato/static/fonts/Comfortaa-Regular.ttf
rubato/static/fonts/Fredoka-Regular.ttf
rubato/static/fonts/Merriweather-Regular.ttf
rubato/static/fonts/Mozart-Regular.ttf
rubato/static/fonts/Roboto-Regular.ttf
rubato/static/fonts/SourceCodePro-Regular.ttf
rubato/static/fonts/__init__.py
rubato/static/png/__init__.py
rubato/static/png/logo_filled.ico
rubato/static/png/logo_filled.png
rubato/structure/__init__.cpython-310-darwin.so
rubato/structure/__init__.py
rubato/structure/scene.cpython-310-darwin.so
rubato/structure/scene.py
rubato/structure/gameobject/__init__.cpython-310-darwin.so
rubato/structure/gameobject/__init__.py
rubato/structure/gameobject/component.cpython-310-darwin.so
rubato/structure/gameobject/component.py
rubato/structure/gameobject/game_object.cpython-310-darwin.so
rubato/structure/gameobject/game_object.py
rubato/structure/gameobject/particles/__init__.cpython-310-darwin.so
rubato/structure/gameobject/particles/__init__.py
rubato/structure/gameobject/particles/particle.cpython-310-darwin.so
rubato/structure/gameobject/particles/particle.py
rubato/structure/gameobject/particles/system.cpython-310-darwin.so
rubato/structure/gameobject/particles/system.py
rubato/structure/gameobject/physics/__init__.cpython-310-darwin.so
rubato/structure/gameobject/physics/__init__.py
rubato/structure/gameobject/physics/engine.cpython-310-darwin.so
rubato/structure/gameobject/physics/engine.py
rubato/structure/gameobject/physics/hitbox.cpython-310-darwin.so
rubato/structure/gameobject/physics/hitbox.py
rubato/structure/gameobject/physics/qtree.cpython-310-darwin.so
rubato/structure/gameobject/physics/qtree.py
rubato-1.0.0.dist-info/LICENSE
rubato-1.0.0.dist-info/METADATA
rubato-1.0.0.dist-info/WHEEL
rubato-1.0.0.dist-info/entry_points.txt
rubato-1.0.0.dist-info/top_level.txt
rubato-1.0.0.dist-info/RECORD
