Metadata-Version: 2.1
Name: rubato
Version: 1.0.0
Summary: A lightweight, developer-first game engine built for Python.
Home-page: https://rubato.app
Download-URL: https://docs.rubato.app/latest/intro
Author: Martin Chaperot, Yamm Elnekave, Tomer Sedan
Author-email: info@rubato.app
License: GPL-3.0
Project-URL: Source, https://github.com/rubatopy/rubato
Project-URL: Issue Tracker, https://github.com/rubatopy/rubato/issues
Project-URL: Documentation, https://docs.rubato.app
Keywords: rubato,game development,education,game engine,engine,physics,sdl,sdl2
Classifier: Development Status :: 5 - Production/Stable
Classifier: Intended Audience :: Education
Classifier: Intended Audience :: Developers
Classifier: License :: OSI Approved :: GNU General Public License v3 or later (GPLv3+)
Classifier: Natural Language :: English
Classifier: Programming Language :: Python
Classifier: Programming Language :: Python :: 3.10
Classifier: Programming Language :: Python :: 3.11
Classifier: Programming Language :: Python :: Implementation :: CPython
Classifier: Topic :: Education
Classifier: Topic :: Games/Entertainment
Classifier: Topic :: Software Development :: Libraries :: Python Modules
Classifier: Topic :: Software Development :: Libraries
Classifier: Typing :: Typed
Requires-Python: >=3.10
License-File: LICENSE
Requires-Dist: PySDL2 (==0.9.*)
Requires-Dist: Cython (==3.0.0a11)
Requires-Dist: pysdl2-dll (==2.24.*)
Requires-Dist: pytiled-parser (==2.2.*)
Provides-Extra: dev
Requires-Dist: pylint (==2.12.*) ; extra == 'dev'
Requires-Dist: yapf (==0.32.*) ; extra == 'dev'
Requires-Dist: pytest (==7.1.*) ; extra == 'dev'
Requires-Dist: pytest-cov (==3.0.*) ; extra == 'dev'
Requires-Dist: psutil (==5.9.*) ; extra == 'dev'
Requires-Dist: pyinstaller (==5.*) ; extra == 'dev'
Requires-Dist: twine ; extra == 'dev'
Requires-Dist: build ; extra == 'dev'
Provides-Extra: docs
Requires-Dist: Sphinx (==5.1.*) ; extra == 'docs'
Requires-Dist: sphinx-autobuild (==2021.3.*) ; extra == 'docs'
Requires-Dist: furo (==2022.6.*) ; extra == 'docs'
Requires-Dist: sphinx-autodoc-typehints (==1.16.*) ; extra == 'docs'
Requires-Dist: sphinx-copybutton (==0.5.*) ; extra == 'docs'
Requires-Dist: sphinx-sitemap (==2.2.*) ; extra == 'docs'
Requires-Dist: sphinx-inline-tabs (==2022.1.2b11) ; extra == 'docs'
Requires-Dist: sphinxext-opengraph (==0.5.*) ; extra == 'docs'
Requires-Dist: sphinx-design (==0.2.*) ; extra == 'docs'
Requires-Dist: sphinx-toolbox (==3.2.0) ; extra == 'docs'
Requires-Dist: enum-tools (==0.9.*) ; extra == 'docs'
